{
  "name": "PLI",
  "scopeName": "source.pli",
  "fileTypes": [
    "pl1",
    "pl",
    "pc",
    "pci",
    "pcx"
  ],
  "patterns": [
    {
      "name": "constant.numeric.pl1",
      "match": "\\b((0(x|X)[0-9a-fA-F]*)|(([0-9]+\\.?[0-9]*)|(\\.[0-9]+))((e|E)(\\+|-)?[0-9]+)?)\\b"
    },
    {
      "name": "comment.block.pl1",
      "begin": "\\/\\*",
      "end": "\\*\\/",
      "contentName": "comment.block.pl1"
    },
    {
      "name": "string.quoted.single.pl1",
      "begin": "'",
      "beginCaptures": {
        "0": {
          "name": "punctuation.definition.string.begin.pl1"
        }
      },
      "end": "'",
      "endCaptures": {
        "0": {
          "name": "punctuation.definition.string.end.pl1"
        }
      },
      "contentName": "string.quoted.single.pl1"
    },
    {
      "match": "(?i:ABNORMAL|ABS|ACOS|ACOSF|ADD|ADDBUFF|ADDR|ADDRDATA|ALIAS|ALIGNED|ALL|ALLOC|ALLOCATE|ALLOCATION|ALLOCN|ALLOCSIZE|ANY|ANYCONDITION|AREA|ASCII|ASIN|ASINF|ASM|ASMTDLI|ASSEMBLER|ASSIGNABLE|ATAN|ATAND|ATANF|ATANH|ATTENTION|ATTN|AUTO|AUTOMATIC|AVAILABLEAREA|BACKWARDS|BASED|BEGIN|BIGENDIAN|BIN|BINARY|BINARYVALUE|BIND|BINVALUE|BIT|BITLOCATION|BKWD|BLKSIZE|BOOL|BUF|BUFFERED|BUFFERS|BUFND|BUFNI|BUFOFF|BUFSP|BUILTIN|BX|BY|BYADDR|BYTE|BYVALUE|B4|CALL|CAST|CDS|CEIL|CENTERLEFT|CENTERRIGHT|CENTRELEFT|CENTRERIGHT|CHAR|CHARACTER|CHARG|CHARGRAPHIC|CHARVAL|CHECK|CHECKSTG|CLOSE|CMPAT|COBOL|COL|COLLATE|COLUMN|COMMENT|COMPARE|COMPILEDATE|COMPILETIME|COMPLETION|COMPLEX|COND|CONDITION|CONJG|CONN|CONNECTED|CONSECUTIVE|CONTROLLED|CONV|CONVERSION|COPY|COS|COSD|COSF|COSH|COUNT|COUNTER|CPLN|CPLX|CS|CSTG|CTL|CTLASA|CTL360|CURRENTSIZE|CURRENTSTORAGE|DATA|DATAFIELD|DATE|DATETIME|DAYS|DAYSTODATE|DAYSTOSECS|DB|DCL|DEC|DECIMAL|DECLARE|DEF|DEFAULT|DEFINE|DEFINED|DELAY|DELETE|DESCRIPTOR|DESCRIPTORS|DFT|DIM|DIMENSION|DIRECT|DISPLAY|DIVIDE|DO|DOWNTHRU|EDIT|ELSE|EMPTY|END|ENDFILE|ENDPAGE|ENTRY|ENTRYADDR|ENV|ENVIRONMENT|EPSILON|ERF|ERFC|ERROR|EVENT|EXCL|EXCLUSIVE|EXIT|EXP|EXPF|EXPONENT|EXPORTS|EXT|EXTERNAL|FB|FBS|FETCH|FILE|FILEDDINT|FILEDDTEST|FILEDDWORD|FILEID|FILEOPEN|FILEREAD|FILESEEK|FILETELL|FILEWRITE|FINISH|FIRST|FILETELL|FILEWRITE|FINISH|FIRST|FIXED|FIXEDOVERFLOW|FLOAT|FLOOR|FLUSH|FOFL|FORMAT|FORTRAN|FREE|FROM|FROMALIEN|FS|GAMMA|GENERIC|GENKEY|GET|GETENV|GO|GOTO|GRAPHIC|GX|HANDLE|HBOUND|HEX|HEXADEC|HEXIMAGE|HIGH|HUGE|IAND|IEEE|IEOR|IF|IGNORE|IMAG|IN|INDEX|INDEXAREA|INDEXED|INIT|INITIAL|INLINE|INOT|INPUT|INT|INTER|INTERNAL|INTO|IOR|IRRED|IRREDUCIBLE|ISIGNED|ISLL|ISMAIN|ISRL|IUNSIGNED|KEY|KEYED|KEYFROM|KEYLENGTH|KEYLOC|KEYTO|LABEL|LAST|LBOUND|LEAVE|LEFT|LENGTH|LIKE|LIMITED|LINE|LINENO|LINESIZE|LINKAGE|LIST|LITTLEENDIAN|LOCATE|LOCATION|LOG|LOGF|LOGGAMMA|LOG10|LOG10F|LOG2|LOW|LOWERCASE|LOWER2|MACCOL|MACLMAR|MACNAME|MACRMAR|MAIN|MAX|MAXEXP|MAXLENGTH|MEMINDEX|MEMSEARCH|MEMVERIFY|MEMVERIFYR|MESEARCHR|MIN|MINEXP|MOD|MPSTR|MULTIPLY|NAME|NATIVE|NCP|NEW|NOCHARG|NOCHARGRAPHIC|NOCHECK|NOCMPAT|NOCONV|NOCONVERSION|NODESCRIPTOR|NOEXECOPS|NOFIXEDOVERFLOW|NOFOFL|NOINLINE|NOLOCK|NOMAP|NOMAPIN|NOMAPOUT|NONASSIGNABLE|NONCONNECTED|NONNATIVE|NOOFL|NOOVERFLOW|NORESCAN|NORMAL|NOSIZE|NOSTRG|NOSTRINGRANGE|NOSTRINGSIZE|NOSTRZ|NOSUBRG|NOSUBSCRIPTRANGE|NOUFL|NOUNDERFLOW|NOWRITE|NOZDIV|NOZERODIVIDE|NULL|OFFSET|OFFSETADD|OFFSETDIFF|OFFSETSUBTRACT|OFFSETVALUE|OFL|OMITTED|ON|ONCHAR|ONCODE|ONCONDCOND|ONCONDID|ONCOUNT|ONFILE|ONGSOURCE|ONKEY|ONLOC|ONSOURCE|ONSUBCODE|ONWCHAR|ONWSOURCE|OPEN|OPTIONAL|OPTIONS|ORDER|ORDINAL|ORDINALNAME|ORDINALPRED|ORDINALSUCC|OTHER|OTHERWISE|OUTPUT|OVERFLOW|PACKAGE|PACKAGENAME|PAGE|PAGENO|PAGESIZE|PARAMETER|PARMSET|PASSWORD|PENDING|PIC|PICTURE|PLACES|PLIASCII|PLICANC|PLICKPT|PLIDELETE|PLIASCII|PLICANC|PLICKPT|PLIDELETE|PLIDUMP|PLIEBCDIC|PLIFILL|PLIFREE|PLIMOVE|PLIOVER|PLIREST|PLIRETC|PLIRETV|PLISAXA|PLISAXB|PLISRTA|PLISRTB|PLISRTC|PLISRTD|PLITDLI|POINTER|POINTERADD|POINTERDIFF|POINTERSUBTRACT|POINTERVALUE|POLY|POS|POSITION|PREC|PRECISION|PRED|PRESENT|PRINT|PRIORITY|PROC|PROCEDURE|PROCEDURENAME|PROD|PTR|PTRADD|PTRVALUE|PUT|PUTENV|QUOTE|RADIX|RAISE2|RANDOM|RANGE|RANK|READ|REAL|RECORD|RECSIZE|RECURSIVE|RED|REDUCIBLE|REENTRANT|REFER|REGIONAL|RELEASE|REM|REORDER|REPATTERN|REPEAT|REPLACEBY2|REPLY|REREAD|RESCAN|RESERVED|RESERVES|RESIGNAL|RESPEC|RETCODE|RETURN|RETURNS|REUSE|REVERSE|REVERT|REWRITE|RIGHT|ROUND|SAMEKEY|SCALARVARYING|SCALE|SEARCH|SEARCHR|SECS|SECSTODATE|SECSTODAYS|SELECT|SEQL|SEQUENTIAL|SERIALIZE4|SET|SIGN|SIGNAL|SIGNED|SIN|SIND|SINF|SINH|SIS|SIZE|SKIP|SNAP|SOURCEFILE|SOURCELINE|SQRT|SQRTF|STATEMENT|STATIC|STATUS|STG|STMT|STOP|STORAGE|STREAM|STRG|STRING|STRINGRANGE|STRINGSIZE|STRUCTURE|STRZ|SUBRG|SUBSCRIPTRANGE|SUBSTR|SUBTRACT|SUCC|SUM|SYSIN|SYSNULL|SYSPARM|SYSPRINT|SYSTEM|SYSVERSION|TALLY|TAN|TAND|TANF|TANH|TASK|THEN|THREADID|TIME|TINY|TITLE|TO|TOTAL|TPK|TPM|TRANSIENT|TRANSLATE|TRANSMIT|TRIM|TRKOFL|TRUNC|TYPE|UFL|UNAL|UNALIGNED|UNALLOCATED|UNBUF|UNBUFFERED|UNDEFINEDFILE|UNDERFLOW|UNDF|UNLOCK|UNSIGNED|UNSPEC|UNTIL|UPDATE|UPPERCASE|UPTHRU|VALID|VALIDDATE|VALUE|VAR|VARGLIST|VARGSIZE|VARIABLE|VARYING|VARYINGZ|VB|VBS|VERIFY|VERIFYR|VS|VSAM|WAIT|WCHAR|WCHARVAL|WEEKDAY|WHEN|WHIGH|WHILE|WIDECHAR|WHEN|WHIGH|WHILE|WIDECHAR|WLOW|WRITE|XMLCHAR|Y4DATE|Y4JULIAN|Y4YEAR|ZDIV|ZERODIVIDE|%INCLUDE|%DECLARE|%DCL)(?=\\s+|;|\\(|\\))",
      "name": "keyword.pli"
    }
  ]
}